xpip_mirror/__init__.py
xpip_mirror/attribute.py
xpip_mirror/cmds.py
xpip_mirror/util.py
xpip_mirror/config/__init__.py
xpip_mirror/config/mirrors.toml
xpip.mirror-1.0.dist-info/LICENSE
xpip.mirror-1.0.dist-info/METADATA
xpip.mirror-1.0.dist-info/WHEEL
xpip.mirror-1.0.dist-info/entry_points.txt
xpip.mirror-1.0.dist-info/top_level.txt
xpip.mirror-1.0.dist-info/zip-safe
xpip.mirror-1.0.dist-info/RECORD
