Metadata-Version: 2.1
Name: xpip.mirror
Version: 1.0
Summary: pip mirror management
Home-page: https://github.com/bondbox/xpip/
Author: Mingzhe Zou
Author-email: zoumingzhe@outlook.com
License: GPLv2
Project-URL: Source Code, https://github.com/bondbox/xpip/
Project-URL: Bug Tracker, https://github.com/bondbox/xpip/issues
Project-URL: Documentation, https://github.com/bondbox/xpip/
Keywords: pip,pypi,mirror
Platform: any
Classifier: Programming Language :: Python
Classifier: Programming Language :: Python :: 3
Requires-Python: >=3.8
License-File: LICENSE
Requires-Dist: ping3
Requires-Dist: pip
Requires-Dist: tabulate
Requires-Dist: toml
Requires-Dist: xarg-python (>=1.3)
